daiso/__init__.py
daiso/alltil.py
daiso-0.0.6.dist-info/METADATA
daiso-0.0.6.dist-info/WHEEL
daiso-0.0.6.dist-info/top_level.txt
daiso-0.0.6.dist-info/RECORD
